Metadata-Version: 1.1
Name: robopager
Version: 0.1.0
Summary: Job monitor and alerting app by Equinox
Home-page: https://github.com/equinoxfitness/robopager
Author: Equinox Fitness
Author-email: UNKNOWN
License: MIT
Keywords: job monitor,daily email check,intraday latency check
Platform: UNKNOWN
Classifier: Development Status :: 5 - Production/Stable
Classifier: Intended Audience :: Developers
Classifier: Natural Language :: English
Classifier: License :: OSI Approved :: MIT License
Classifier: Programming Language :: Python :: 3.6
